igniteworks/__init__.py
igniteworks/client/__init__.py
igniteworks/client/connection.py
igniteworks/client/cursor.py
igniteworks/client/exceptions.py
igniteworks/client/ignite.py
igniteworks/client/sql_test.py
igniteworks/sqlalchemy/__init__.py
igniteworks/sqlalchemy/dialect.py
igniteworks/sqlalchemy/example.py
igniteworks/sqlalchemy/types.py
sqlalchemy_ignite-0.5.0.dist-info/LICENSE.txt
sqlalchemy_ignite-0.5.0.dist-info/METADATA
sqlalchemy_ignite-0.5.0.dist-info/WHEEL
sqlalchemy_ignite-0.5.0.dist-info/entry_points.txt
sqlalchemy_ignite-0.5.0.dist-info/top_level.txt
sqlalchemy_ignite-0.5.0.dist-info/RECORD
