Metadata-Version: 2.1
Name: sqlalchemy-ignite
Version: 0.5.0
Summary: SQLAlchemy dialect for Apache Ignite
Home-page: https://github.com/predictiveworks/sqlalchemy-ignite/
Author: Dr. Stefan Krusche
Author-email: krusche@dr-kruscheundpartner.de
License: Apache License Version 2.0
Platform: UNKNOWN
Classifier: Development Status :: 3 - Alpha
Classifier: Intended Audience :: Developers
Classifier: License :: OSI Approved :: Apache Software License
Classifier: Operating System :: OS Independent
Classifier: Programming Language :: Python
Classifier: Programming Language :: Python :: 3.8
Classifier: Programming Language :: Python :: 3.9
Classifier: Programming Language :: Python :: Implementation :: PyPy
Classifier: Programming Language :: SQL
Classifier: Topic :: Database
Classifier: Topic :: Database :: Front-Ends
Classifier: Topic :: Software Development
Classifier: Topic :: Software Development :: Libraries :: Python Modules
License-File: LICENSE.txt
Requires-Dist: pyignite (>=0.5.2)
Requires-Dist: sqlalchemy (>=1.2.0)
Provides-Extra: test
Requires-Dist: pytest (>=2.5.2) ; extra == 'test'
Requires-Dist: mock (>=1.0.1) ; extra == 'test'
